zaiq/__init__.py
zaiq-0.0.1.dist-info/METADATA
zaiq-0.0.1.dist-info/WHEEL
zaiq-0.0.1.dist-info/entry_points.txt
zaiq-0.0.1.dist-info/RECORD
