Metadata-Version: 2.4
Name: zaiq
Version: 0.0.1
Summary: zaiq - AI Capacity Orchestrator. Steady distribution of surplus AI capacity through intelligent queueing.
Project-URL: Homepage, https://zaiq-dev.com
Project-URL: Documentation, https://github.com/zaiq-dev/zaiq
Project-URL: Repository, https://github.com/zaiq-dev/zaiq.git
Project-URL: Bug Tracker, https://github.com/zaiq-dev/zaiq/issues
Author: zaiq-dev
License-Expression: MIT
Keywords: ai,automation,bmad,capacity,claude,development,orchestrator,queue,singapore
Classifier: Development Status :: 2 - Pre-Alpha
Classifier: Intended Audience :: Developers
Classifier: License :: OSI Approved :: MIT License
Classifier: Programming Language :: Python :: 3
Classifier: Programming Language :: Python :: 3.8
Classifier: Programming Language :: Python :: 3.9
Classifier: Programming Language :: Python :: 3.10
Classifier: Programming Language :: Python :: 3.11
Classifier: Programming Language :: Python :: 3.12
Classifier: Topic :: Software Development :: Libraries :: Python Modules
Classifier: Topic :: System :: Systems Administration
Requires-Python: >=3.8
